{
  "main": {
    "id": "4387f5661cb25858",
    "type": "split",
    "children": [
      {
        "id": "b4d895df021eb3fc",
        "type": "tabs",
        "children": [
          {
            "id": "1f57f79ad26b86c5",
            "type": "leaf",
            "state": {
              "type": "markdown",
              "state": {
                "file": "newcomer-guide.md",
                "mode": "preview",
                "source": false
              },
              "icon": "lucide-file",
              "title": "newcomer-guide"
            }
          }
        ]
      }
    ],
    "direction": "vertical"
  },
  "left": {
    "id": "2b57ec6b2d88e4a8",
    "type": "split",
    "children": [
      {
        "id": "6a66a166ceb0f3bd",
        "type": "tabs",
        "children": [
          {
            "id": "f88a7b9d1447bdb4",
            "type": "leaf",
            "state": {
              "type": "file-explorer",
              "state": {
                "sortOrder": "alphabetical",
                "autoReveal": false
              },
              "icon": "lucide-folder-closed",
              "title": "文件列表"
            }
          },
          {
            "id": "833cf5813ff0f2b1",
            "type": "leaf",
            "state": {
              "type": "search",
              "state": {
                "query": "",
                "matchingCase": false,
                "explainSearch": false,
                "collapseAll": false,
                "extraContext": false,
                "sortOrder": "alphabetical"
              },
              "icon": "lucide-search",
              "title": "搜索"
            }
          },
          {
            "id": "c6cf5515f95ac934",
            "type": "leaf",
            "state": {
              "type": "bookmarks",
              "state": {},
              "icon": "lucide-bookmark",
              "title": "书签"
            }
          }
        ]
      }
    ],
    "direction": "horizontal",
    "width": 200
  },
  "right": {
    "id": "2f323e994925f346",
    "type": "split",
    "children": [
      {
        "id": "488849e5d13f6afa",
        "type": "tabs",
        "children": [
          {
            "id": "24ffeb744dbeb4db",
            "type": "leaf",
            "state": {
              "type": "backlink",
              "state": {
                "file": "newcomer-guide.md",
                "collapseAll": false,
                "extraContext": false,
                "sortOrder": "alphabetical",
                "showSearch": false,
                "searchQuery": "",
                "backlinkCollapsed": false,
                "unlinkedCollapsed": true
              },
              "icon": "links-coming-in",
              "title": "newcomer-guide 的反向链接列表"
            }
          },
          {
            "id": "6f4e586512fa1c00",
            "type": "leaf",
            "state": {
              "type": "outgoing-link",
              "state": {
                "file": "newcomer-guide.md",
                "linksCollapsed": false,
                "unlinkedCollapsed": true
              },
              "icon": "links-going-out",
              "title": "newcomer-guide 的出链列表"
            }
          },
          {
            "id": "ce52799517e1f08a",
            "type": "leaf",
            "state": {
              "type": "tag",
              "state": {
                "sortOrder": "frequency",
                "useHierarchy": true,
                "showSearch": false,
                "searchQuery": ""
              },
              "icon": "lucide-tags",
              "title": "标签"
            }
          },
          {
            "id": "29e84d2ba6d3d141",
            "type": "leaf",
            "state": {
              "type": "outline",
              "state": {
                "file": "newcomer-guide.md",
                "followCursor": false,
                "showSearch": false,
                "searchQuery": ""
              },
              "icon": "lucide-list",
              "title": "newcomer-guide 的大纲"
            }
          }
        ]
      }
    ],
    "direction": "horizontal",
    "width": 300,
    "collapsed": true
  },
  "left-ribbon": {
    "hiddenItems": {
      "switcher:打开快速切换": false,
      "graph:查看关系图谱": false,
      "canvas:新建白板": false,
      "daily-notes:打开/创建今天的日记": false,
      "templates:插入模板": false,
      "command-palette:打开命令面板": false
    }
  },
  "active": "1f57f79ad26b86c5",
  "lastOpenFiles": [
    "GitHub/Flowchart.png",
    "GitHub/exported_image.png",
    "Home.md",
    "work",
    "newcomer-guide.md",
    "node/node-Homepage-Download-Guide.png",
    "daily/Work Ledger.md",
    "daily"
  ]
}